setup.py
tutorial_package_pumpkins/__init__.py
tutorial_package_pumpkins/greet.py
tutorial_package_pumpkins.egg-info/PKG-INFO
tutorial_package_pumpkins.egg-info/SOURCES.txt
tutorial_package_pumpkins.egg-info/dependency_links.txt
tutorial_package_pumpkins.egg-info/requires.txt
tutorial_package_pumpkins.egg-info/top_level.txt