Metadata-Version: 1.0
Name: tutorial-package-pumpkins
Version: 0.0.2
Summary: A demonstration of how to create and publish python packages
Home-page: UNKNOWN
Author: Jarunan Panyasantisuk
Author-email: jarunan@ethz.ch
License: BSD
Platform: UNKNOWN
